checkpointlib/__init__.py
checkpointlib/checkpointlib.py
checkpointlib-0.0.2.dist-info/METADATA
checkpointlib-0.0.2.dist-info/WHEEL
checkpointlib-0.0.2.dist-info/licenses/LICENSE
checkpointlib-0.0.2.dist-info/RECORD
