Metadata-Version: 2.1
Name: checkpointlib
Version: 0.0.2
Summary: A package to send ML training checkpoints online in Python
Project-URL: Homepage, https://github.com/kendasi/checkpointlib
Project-URL: Bug Tracker, https://github.com/kendasi/checkpointlib/issues
Author-email: Kendasi <info@kendasi.com>
License-File: LICENSE
Classifier: License :: OSI Approved :: MIT License
Classifier: Operating System :: OS Independent
Classifier: Programming Language :: Python :: 3
Requires-Python: >=3.8
